[
  {
    "name": "Administration",
    "id": "administration",
    "img": "cat/administration.png"
  },
  {
    "name": "Social work",
    "id": "socialWork",
    "img": "cat/socialWork.png"
  },
  {
    "name": "Accounting",
    "id": "accounting",
    "img": "cat/accounting.png"
  },
  {
    "name": "Humanities",
    "id": "humanities",
    "img": "cat/humanities.png"
  },
  {
    "name": "Engineering",
    "id": "engineering",
    "img": "cat/engineering.png"
  },
  {
    "name": "Medical Studies",
    "id": "medicalStudies",
    "img": "cat/medical.png"
  },
  {
    "name": "Education",
    "id": "education",
    "img": "cat/education.png"
  },
  {
    "name": "Architecture",
    "id": "architecture",
    "img": "cat/architecture.png"
  },
  {
    "name": "Computer Science",
    "id": "computerScience",
    "img": "cat/computerScience.png"
  },
  {
    "name": "Psychology",
    "id": "psychology",
    "img": "cat/psychology.png"
  },
  {
    "name": "Social Sciences",
    "id": "socialSciences",
    "img": "cat/socialSciences.png"
  },
  {
    "name": "Communication",
    "id": "communication",
    "img": "cat/communication.png"
  }
]
